purectypes/__init__.py
purectypes/dump.py
purectypes/generators.py
purectypes/pack.py
purectypes/struct_value.py
purectypes/types.py
purectypes/union_value.py
purectypes/unpack.py
purectypes-0.2.dist-info/LICENSE.txt
purectypes-0.2.dist-info/METADATA
purectypes-0.2.dist-info/WHEEL
purectypes-0.2.dist-info/top_level.txt
purectypes-0.2.dist-info/RECORD
