Metadata-Version: 2.1
Name: purectypes
Version: 0.2
Summary: pure-python C types packer/unpacker
Home-page: https://github.com/aguinet/purectypes
Author: Adrien Guinet
Author-email: adrien@guinet.me
License: Apache 2.0
Keywords: ffi ctypes
Platform: UNKNOWN
Classifier: Development Status :: 4 - Beta
Classifier: Intended Audience :: Science/Research
Classifier: Intended Audience :: Developers
Classifier: Topic :: Software Development :: Build Tools
Classifier: Topic :: Scientific/Engineering
Classifier: License :: OSI Approved :: Apache Software License
Classifier: Programming Language :: Python :: 3
Classifier: Programming Language :: Python :: 3.2
Classifier: Programming Language :: Python :: 3.3
Classifier: Programming Language :: Python :: 3.4
Classifier: Programming Language :: Python :: 3.5
Classifier: Programming Language :: Python :: 3.6
Classifier: Programming Language :: Python :: 3.7
Classifier: Programming Language :: Python :: 3.8
Requires-Python: !=3.0.*, !=3.1.*, !=3.2.*, <4
